migrado/__init__.py
migrado/constants.py
migrado/db_client.py
migrado/migrado.py
migrado/utils.py
migrado-0.6.11.dist-info/LICENSE.txt
migrado-0.6.11.dist-info/METADATA
migrado-0.6.11.dist-info/WHEEL
migrado-0.6.11.dist-info/entry_points.txt
migrado-0.6.11.dist-info/RECORD
