Metadata-Version: 2.1
Name: migrado
Version: 0.6.11
Summary: ArangoDB migrations and batch processing manager
Home-page: https://github.com/protojour/migrado
License: MIT
Author: Eirik Krogstad
Author-email: eirikkr@gmail.com
Requires-Python: >=3.8,<4.0
Classifier: License :: OSI Approved :: MIT License
Classifier: Programming Language :: Python :: 3
Classifier: Programming Language :: Python :: 3.8
Classifier: Programming Language :: Python :: 3.9
Classifier: Programming Language :: Python :: 3.10
Classifier: Programming Language :: Python :: 3.11
Requires-Dist: click (>=8.1.3,<9.0.0)
Requires-Dist: python-arango (>=7.7.0,<8.0.0)
Requires-Dist: pyyaml (>=6.0.1,<7.0.0)
Requires-Dist: rich (>=10.12.0,<11.0.0)
Project-URL: Repository, https://github.com/protojour/migrado
